testimony/__init__.py
testimony/cli.py
testimony/config.py
testimony/constants.py
testimony/parser.py
testimony-2.4.0.dist-info/LICENSE
testimony-2.4.0.dist-info/METADATA
testimony-2.4.0.dist-info/WHEEL
testimony-2.4.0.dist-info/entry_points.txt
testimony-2.4.0.dist-info/top_level.txt
testimony-2.4.0.dist-info/RECORD
