Metadata-Version: 2.1
Name: testimony
Version: 2.4.0
Summary: Testimony inspects and reports on the python test cases.
Home-page: https://github.com/SatelliteQE/testimony/
Author: Suresh Thirugn
Author-email: sthirugn@redhat.com
Classifier: Development Status :: 5 - Production/Stable
Classifier: Intended Audience :: Developers
Classifier: License :: OSI Approved :: GNU General Public License v3 (GPLv3)
Classifier: Programming Language :: Python :: 3 :: Only
Classifier: Programming Language :: Python :: 3
Classifier: Programming Language :: Python :: 3.8
Classifier: Programming Language :: Python :: 3.9
Classifier: Programming Language :: Python :: 3.10
Classifier: Programming Language :: Python :: 3.11
License-File: LICENSE
Requires-Dist: Click
Requires-Dist: termcolor
Requires-Dist: docutils
Requires-Dist: pyyaml
